{
    "name": "Spice Kingdom",
    "address": {
        "street": "456 Curry Lane",
        "city": "Kanpur",
        "state": "Uttar Pradesh",
        "country": "India",
        "zip": "SW1A1AA"
    },
    "menu": [
        {
            "name": "Chicken Tikka Masala",
            "description": "Grilled chicken in a spiced tomato sauce, served with basmati rice",
            "price": 11.99,
            "image": "https://example.com/images/chicken_tikka_masala.jpg"
        },
        {
            "name": "Vegetable Biryani",
            "description": "Fragrant rice cooked with mixed vegetables and aromatic spices",
            "price": 9.99,
            "image": "https://example.com/images/vegetable_biryani.jpg"
        },
        {
            "name": "Gulab Jamun",
            "description": "Sweet milk dumplings soaked in rose-flavored syrup",
            "price": 4.99,
            "image": "https://example.com/images/gulab_jamun.jpg"
        }
    ]
}

